<?xml version="1.0" encoding="utf-8"?>
<SoundBanksInfo Platform="PS4" SchemaVersion="10" SoundbankVersion="112">
	<RootPaths>
		<ProjectRoot>C:\stingray\projects\rtsdev\rts_wwise\</ProjectRoot>
		<SourceFilesRoot>C:\stingray\projects\rtsdev\rts_wwise\.cache\PS4\</SourceFilesRoot>
		<SoundBanksRoot>C:\stingray\projects\rtsdev\rts_wwise\GeneratedSoundBanks\PS4\</SoundBanksRoot>
		<ExternalSourcesInputFile></ExternalSourcesInputFile>
		<ExternalSourcesOutputRoot>C:\stingray\projects\rtsdev\rts_wwise\GeneratedSoundBanks\PS4</ExternalSourcesOutputRoot>
	</RootPaths>
	<SoundBanks>
		<SoundBank Id="1355168291" Language="SFX">
			<ShortName>Init</ShortName>
			<Path>Init.bnk</Path>
		</SoundBank>
	</SoundBanks>
</SoundBanksInfo>
